Metadata-Version: 2.1
Name: misha-lib
Version: 0.0.1
Summary: My Package
Author: Misha Astanin
Author-email: misha100904@gmail.com
